adk_dynamodb_session/__init__.py
adk_dynamodb_session/_models.py
adk_dynamodb_session/_session_service.py
adk_dynamodb_session-0.0.5.dist-info/METADATA
adk_dynamodb_session-0.0.5.dist-info/WHEEL
adk_dynamodb_session-0.0.5.dist-info/licenses/LICENSE
adk_dynamodb_session-0.0.5.dist-info/RECORD
